amrs/__init__.py
amrs-0.0.0.dist-info/LICENSE
amrs-0.0.0.dist-info/METADATA
amrs-0.0.0.dist-info/WHEEL
amrs-0.0.0.dist-info/RECORD
