Metadata-Version: 2.3
Name: AMRS
Version: 0.0.0
Summary: The adaptive model routing system for exploration and exploitation.
License: MIT
Author: InftyAI
Requires-Python: >=3.10,<4.0
Classifier: License :: OSI Approved :: MIT License
Classifier: Programming Language :: Python :: 3
Classifier: Programming Language :: Python :: 3.10
Classifier: Programming Language :: Python :: 3.11
Classifier: Programming Language :: Python :: 3.12
Classifier: Programming Language :: Python :: 3.13
